kh_common/__init__.py
kh_common/backblaze.py
kh_common/base64.py
kh_common/blocking.py
kh_common/crawling.py
kh_common/crc.py
kh_common/cwd.py
kh_common/datetime.py
kh_common/email.py
kh_common/gateway.py
kh_common/hashing.py
kh_common/logging.py
kh_common/map.py
kh_common/message_queue.py
kh_common/safe_join.py
kh_common/auth/__init__.py
kh_common/caching/__init__.py
kh_common/caching/integer.py
kh_common/caching/key_value_store.py
kh_common/config/__init__.py
kh_common/config/calculated.py
kh_common/config/constants.py
kh_common/config/credentials.py
kh_common/config/repo.py
kh_common/exceptions/__init__.py
kh_common/exceptions/base_error.py
kh_common/exceptions/http_error.py
kh_common/models/__init__.py
kh_common/models/auth.py
kh_common/models/privacy.py
kh_common/models/rating.py
kh_common/models/telegram.py
kh_common/models/user.py
kh_common/models/verified.py
kh_common/server/__init__.py
kh_common/server/middleware/__init__.py
kh_common/server/middleware/auth.py
kh_common/server/middleware/cors.py
kh_common/sql/__init__.py
kh_common/sql/query.py
kh_common/telegram/__init__.py
kh_common/timing/__init__.py
kh_common/utilities/__init__.py
kh_common/utilities/json.py
kh_common/utilities/signal.py
kh_common/utilities/speed.py
tests/utilities/__init__.py
tests/utilities/aerospike.py
tests/utilities/auth.py
tests/utilities/caching.py
tests/utilities/credentials.py
tests/utilities/requests.py
kh_common-0.7.1.dist-info/LICENSE
kh_common-0.7.1.dist-info/METADATA
kh_common-0.7.1.dist-info/WHEEL
kh_common-0.7.1.dist-info/top_level.txt
kh_common-0.7.1.dist-info/RECORD
