Metadata-Version: 2.1
Name: kh-common
Version: 0.7.1
Summary: common libraries for kheina.com
Home-page: https://github.com/kheina-com/kh-common
Author: kheina
License: Mozilla Public License 2.0
Requires-Python: >=3.9.*
License-File: LICENSE
Requires-Dist: setuptools (~=66.1.1)
Requires-Dist: ujson (~=5.5.0)
Requires-Dist: requests (~=2.28.1)
Requires-Dist: aiohttp (~=3.7.3)
Requires-Dist: fastapi (~=0.89.1)
Requires-Dist: pydantic (~=1.9.0)
Provides-Extra: aerospike
Requires-Dist: aerospike (~=7.0.2) ; extra == 'aerospike'
Provides-Extra: auth
Requires-Dist: cryptography (~=3.0) ; extra == 'auth'
Requires-Dist: aerospike (~=7.0.2) ; extra == 'auth'
Provides-Extra: build
Requires-Dist: wheel (~=0.38.4) ; extra == 'build'
Requires-Dist: twine (~=3.4.2) ; extra == 'build'
Requires-Dist: pytest (~=6.2.1) ; extra == 'build'
Requires-Dist: pytest-asyncio (~=0.14.0) ; extra == 'build'
Requires-Dist: pytest-mock (~=3.4.0) ; extra == 'build'
Requires-Dist: isort (~=5.11.4) ; extra == 'build'
Requires-Dist: pytest-aiohttp (~=0.3.0) ; extra == 'build'
Requires-Dist: pytest-cov (~=3.0.0) ; extra == 'build'
Requires-Dist: pytest-env (~=0.6.2) ; extra == 'build'
Requires-Dist: httpx (~=0.23.1) ; extra == 'build'
Provides-Extra: logging
Requires-Dist: google-cloud-logging (~=3.2.2) ; extra == 'logging'
Provides-Extra: mq
Requires-Dist: pika (~=1.1.0) ; extra == 'mq'
Provides-Extra: sql
Requires-Dist: psycopg2-binary (==2.9.3) ; extra == 'sql'
